{
	"name": "pl_http_adls",
	"properties": {
		"activities": [
			{
				"name": "Copy data1",
				"type": "Copy",
				"dependsOn": [],
				"policy": {
					"timeout": "7.00:00:00",
					"retry": 0,
					"retryIntervalInSeconds": 30,
					"secureOutput": false,
					"secureInput": false
				},
				"userProperties": [],
				"typeProperties": {
					"source": {
						"type": "ExcelSource",
						"additionalColumns": [
							{
								"name": "name",
								"value": "$$FILEPATH"
							}
						],
						"storeSettings": {
							"type": "HttpReadSettings",
							"requestMethod": "GET"
						}
					},
					"sink": {
						"type": "DelimitedTextSink",
						"storeSettings": {
							"type": "AzureBlobFSWriteSettings"
						},
						"formatSettings": {
							"type": "DelimitedTextWriteSettings",
							"quoteAllText": true,
							"fileExtension": " "
						}
					},
					"enableStaging": false,
					"translator": {
						"type": "TabularTranslator",
						"mappings": [
							{
								"source": {
									"name": "First Name",
									"type": "String",
									"physicalType": "String"
								},
								"sink": {
									"name": "First Name",
									"type": "String",
									"physicalType": "String"
								}
							},
							{
								"source": {
									"name": "Last Name",
									"type": "String",
									"physicalType": "String"
								},
								"sink": {
									"name": "Last Name",
									"type": "String",
									"physicalType": "String"
								}
							},
							{
								"source": {
									"name": "Gender",
									"type": "String",
									"physicalType": "String"
								},
								"sink": {
									"name": "Gender",
									"type": "String",
									"physicalType": "String"
								}
							},
							{
								"source": {
									"name": "Country",
									"type": "String",
									"physicalType": "String"
								},
								"sink": {
									"name": "Country",
									"type": "String",
									"physicalType": "String"
								}
							},
							{
								"source": {
									"name": "Age",
									"type": "String",
									"physicalType": "String"
								},
								"sink": {
									"name": "Age",
									"type": "String",
									"physicalType": "String"
								}
							},
							{
								"source": {
									"name": "Date",
									"type": "String",
									"physicalType": "String"
								},
								"sink": {
									"name": "Date",
									"type": "String",
									"physicalType": "String"
								}
							},
							{
								"source": {
									"name": "Id",
									"type": "String",
									"physicalType": "String"
								},
								"sink": {
									"name": "Id",
									"type": "String",
									"physicalType": "String"
								}
							},
							{
								"source": {
									"name": "name",
									"type": "String"
								},
								"sink": {
									"name": "name",
									"type": "String",
									"physicalType": "String"
								}
							}
						],
						"typeConversion": true,
						"typeConversionSettings": {
							"allowDataTruncation": true,
							"treatBooleanAsNumber": false
						}
					}
				},
				"inputs": [
					{
						"referenceName": "dshttpxl",
						"type": "DatasetReference"
					}
				],
				"outputs": [
					{
						"referenceName": "dscontainerhttp",
						"type": "DatasetReference"
					}
				]
			}
		],
		"annotations": []
	}
}